Metadata-Version: 1.1
Name: what-the-license
Version: 0.1
Summary: Returns the content of a jar file's MANIFEST as dict.
Home-page: http://github.com/nlohmann/what_the_license
Author: Niels Lohmann
Author-email: mail@nlohmann.me
License: MIT
Keywords: open source license file(1)
Platform: UNKNOWN
Classifier: Development Status :: 4 - Beta
Classifier: License :: OSI Approved :: MIT License
Classifier: Programming Language :: Python :: 2.7
